__init__.py
lowerlvl/__init__.py
lowerlvl/lowerlvl.py
lowerlvl-1.5.2.dist-info/LICENSE
lowerlvl-1.5.2.dist-info/METADATA
lowerlvl-1.5.2.dist-info/WHEEL
lowerlvl-1.5.2.dist-info/top_level.txt
lowerlvl-1.5.2.dist-info/RECORD
