Metadata-Version: 2.2
Name: lowerlvl
Version: 1.5.2
Summary: A package that retrieves low-level system data on macOS.
Author-email: Borne Sanders <b@matrixsystemsgroup.com>
License: Copyright <2025> <Borne Sanders>
Project-URL: Homepage, https://github.com/BorneNeedsHelp
Project-URL: Repository, https://github.com/BorneNeedsHelp/lowerlvl
Project-URL: Issues, https://github.com/BorneNeedsHelp/lowerlvl/issues
Keywords: macOS,system,hardware,Apple
Classifier: Development Status :: 3 - Alpha
Classifier: Programming Language :: Python :: 3.12
Classifier: License :: OSI Approved :: MIT License
Classifier: Operating System :: MacOS
Requires-Python: >=3.12
License-File: LICENSE
Requires-Dist: pyobjc
